matrix_bgpsim/__init__.py
matrix_bgpsim-1.0.1.dist-info/licenses/LICENSE
matrix_bgpsim-1.0.1.dist-info/METADATA
matrix_bgpsim-1.0.1.dist-info/WHEEL
matrix_bgpsim-1.0.1.dist-info/top_level.txt
matrix_bgpsim-1.0.1.dist-info/RECORD
