Metadata-Version: 2.4
Name: matrix-bgpsim
Version: 1.0.1
Summary: Matrix-based BGP simulation tool for AS-level routing analysis, supporting GPU acceleration.
Author-email: Yihao Chen <yh-chen21@mails.tsinghua.edu.cn>
License: MIT
Project-URL: Homepage, https://github.com/yhchen-tsinghua/matrix-bgpsim
Project-URL: Repository, https://github.com/yhchen-tsinghua/matrix-bgpsim
Project-URL: Issues, https://github.com/yhchen-tsinghua/matrix-bgpsim/issues
Project-URL: Documentation, https://matrix-bgpsim.readthedocs.io/en/latest/
Keywords: bgp,simulation,networking,as-level,gpu
Classifier: Development Status :: 5 - Production/Stable
Classifier: Programming Language :: Python :: 3
Classifier: Programming Language :: Python :: 3.8
Classifier: Programming Language :: Python :: 3.9
Classifier: Programming Language :: Python :: 3.10
Classifier: Programming Language :: Python :: 3.11
Classifier: Programming Language :: Python :: 3.12
Classifier: License :: OSI Approved :: MIT License
Classifier: Operating System :: OS Independent
Classifier: Topic :: Internet
Classifier: Topic :: System :: Networking
Requires-Python: >=3.8
License-File: LICENSE
Requires-Dist: lz4
Requires-Dist: numpy>=1.21
Provides-Extra: torch
Requires-Dist: torch>=2.0.0; extra == "torch"
Provides-Extra: cupy
Requires-Dist: cupy>=12.0.0; extra == "cupy"
Dynamic: license-file
